sunpal/__init__.py
sunpal/api_error.py
sunpal/compat.py
sunpal/environment.py
sunpal/http_request.py
sunpal/list_result.py
sunpal/main.py
sunpal/model.py
sunpal/request.py
sunpal/result.py
sunpal/util.py
sunpal/version.py
sunpal/models/__init__.py
sunpal/models/consulta.py
sunpal/models/customers.py
sunpal/models/interactive.py
tests/__init__.py
tests/address.py
tests/consulta.py
tests/customer_update.py
tests/customers.py
tests/interactive.py
tests/request.py
tests/send_nip.py
tests/views.py
sunpal-0.1.12.dist-info/LICENSE.txt
sunpal-0.1.12.dist-info/METADATA
sunpal-0.1.12.dist-info/WHEEL
sunpal-0.1.12.dist-info/top_level.txt
sunpal-0.1.12.dist-info/RECORD
