Metadata-Version: 2.1
Name: sunpal
Version: 0.1.12
Summary: Sunpal small library devs
Home-page: https://sunpal.readthedocs.io/
Author: sunwise
Author-email: abner@sunwise.io
License: MIT
Classifier: Intended Audience :: Developers
Classifier: License :: OSI Approved :: MIT License
Classifier: Programming Language :: Python
Classifier: Programming Language :: Python :: 3
Classifier: Programming Language :: Python :: 3.6
Classifier: Programming Language :: Python :: 3.7
Classifier: Programming Language :: Python :: 3.8
Classifier: Programming Language :: Python :: 3.9
Classifier: Operating System :: OS Independent
License-File: LICENSE.txt
Requires-Dist: requests
